agentweaver/__init__.py
agentweaver-0.0.0.dist-info/METADATA
agentweaver-0.0.0.dist-info/WHEEL
agentweaver-0.0.0.dist-info/top_level.txt
agentweaver-0.0.0.dist-info/RECORD
